easy_gscv/__init__.py
easy_gscv/models.py
easy_gscv-0.2.dist-info/METADATA
easy_gscv-0.2.dist-info/RECORD
easy_gscv-0.2.dist-info/WHEEL
easy_gscv-0.2.dist-info/top_level.txt
test/__init__.py
test/test_gscv.py
