Metadata-Version: 2.1
Name: easy-gscv
Version: 0.2
Summary: A high level library gridsearch / cross evaluation library for scikit-learn
Home-page: https://github.com/Jasper-Koops/easy-gscv
Author: Jasper Koops
Author-email: jasperkoops91@gmail.com
License: UNKNOWN
Platform: UNKNOWN
Classifier: Programming Language :: Python :: 3.7
Classifier: License :: OSI Approved :: MIT License
Classifier: Operating System :: OS Independent
Requires-Dist: numpy
Requires-Dist: scipy
Requires-Dist: scikit-learn
